<?xml version="1.0" encoding="utf-8" ?>
<dwsync>
<file name="ajcpanel.css" server="C:/Documents and Settings/Admin/Рабочий стол/triple_champion1/triple_champion/" local="130662606780000000" remote="130662606780000000" />
<file name="component.css" server="C:/Documents and Settings/Admin/Рабочий стол/triple_champion1/triple_champion/" local="130662606800000000" remote="130662606800000000" />
<file name="index.html" server="C:/Documents and Settings/Admin/Рабочий стол/triple_champion1/triple_champion/" local="130662606800000000" remote="130662606800000000" />
<file name="ugol_Night_l.css" server="C:/Documents and Settings/Admin/Рабочий стол/triple_champion1/triple_champion/" local="130662606800000000" remote="130662606800000000" />
<file name="ugol_Night_r.css" server="C:/Documents and Settings/Admin/Рабочий стол/triple_champion1/triple_champion/" local="130662606800000000" remote="130662606800000000" />
<file name="ugol_Rich_l.css" server="C:/Documents and Settings/Admin/Рабочий стол/triple_champion1/triple_champion/" local="130662606800000000" remote="130662606800000000" />
<file name="ugol_Rich_r.css" server="C:/Documents and Settings/Admin/Рабочий стол/triple_champion1/triple_champion/" local="130662606800000000" remote="130662606800000000" />
<file name="ugol_Sky_l.css" server="C:/Documents and Settings/Admin/Рабочий стол/triple_champion1/triple_champion/" local="130662606820000000" remote="130662606820000000" />
<file name="ugol_Sky_r.css" server="C:/Documents and Settings/Admin/Рабочий стол/triple_champion1/triple_champion/" local="130662606820000000" remote="130662606820000000" />
</dwsync>